<h:html xmlns:h="http://www.w3.org/1999/xhtml" xmlns:orx="http://openrosa.org/jr/xforms" xmlns="http://www.w3.org/2002/xforms" xmlns:xsd="http://www.w3.org/2001/XMLSchema" xmlns:jr="http://openrosa.org/javarosa" xmlns:vellum="http://commcarehq.org/xforms/vellum">
	<h:head>
		<h:title>Nurse &amp; Doctor Duty</h:title>
		<model>
			<instance>
				<data xmlns:jrm="http://dev.commcarehq.org/jr/xforms" xmlns="http://openrosa.org/formdesigner/2FC99CAF-355B-4709-A363-67B2AF485509" uiVersion="1" version="626" name="Nurse &amp; Doctor Duty">
					<nurse_on_call/>
					<shift/>
					<on_call_doctor/>
				<orx:meta xmlns:cc="http://commcarehq.org/xforms"><orx:deviceID/><orx:timeStart/><orx:timeEnd/><orx:username/><orx:userID/><orx:instanceID/><cc:appVersion/></orx:meta></data>
			</instance><instance id="commcaresession" src="jr://instance/session"/>
			<bind nodeset="/data/nurse_on_call" required="true()"/>
			<bind nodeset="/data/shift"/>
			<bind nodeset="/data/on_call_doctor"/>
			<itext>
				<translation lang="en" default="">
					<text id="nurse_on_call-label">
						<value>Nurse on Duty:</value>
					</text>
					<text id="nurse_on_call-nurse_1-label">
						<value>nurse 1</value>
					</text>
					<text id="nurse_on_call-nurse_2-label">
						<value>nurse 2</value>
					</text>
					<text id="nurse_on_call-nurse_3-label">
						<value>nurse 3</value>
					</text>
					<text id="nurse_on_call-nurse_4-label">
						<value>nurse 4</value>
					</text>
					<text id="nurse_on_call-nurse_5-label">
						<value>nurse 5</value>
					</text>
					<text id="nurse_on_call-nurse_6-label">
						<value>nurse 6</value>
					</text>
					<text id="nurse_on_call-nurse_7-label">
						<value>nurse 7</value>
					</text>
					<text id="nurse_on_call-nurse_8-label">
						<value>nurse 8</value>
					</text>
					<text id="nurse_on_call-nurse_9-label">
						<value>nurse 9</value>
					</text>
					<text id="nurse_on_call-nurse_10-label">
						<value>nurse 10</value>
					</text>
					<text id="shift-label">
						<value>Shift</value>
					</text>
					<text id="shift-morning-label">
						<value>Morning (8am - 4pm)</value>
					</text>
					<text id="shift-afternoon-label">
						<value>Afternoon (4pm - 12am)</value>
					</text>
					<text id="shift-night-label">
						<value>Night (12am - 8am)</value>
					</text>
					<text id="on_call_doctor-label">
						<value>On-call Doctor:</value>
					</text>
					<text id="on_call_doctor-doctor_1-label">
						<value>Dr. ____ ____ (PG) (phone number)</value>
					</text>
					<text id="on_call_doctor-doctor_2-label">
						<value>Dr. ____ ____ (SR) (phone number)</value>
					</text>
					<text id="on_call_doctor-doctor_3-label">
						<value>Dr. ____ ____ (Attending) (phone number)</value>
					</text>
				</translation>
				<translation lang="hin">
					<text id="nurse_on_call-label">
						<value>Nurse on Duty:</value>
					</text>
					<text id="nurse_on_call-nurse_1-label">
						<value>nurse 1</value>
					</text>
					<text id="nurse_on_call-nurse_2-label">
						<value>nurse 2</value>
					</text>
					<text id="nurse_on_call-nurse_3-label">
						<value>nurse 3</value>
					</text>
					<text id="nurse_on_call-nurse_4-label">
						<value>nurse 4</value>
					</text>
					<text id="nurse_on_call-nurse_5-label">
						<value>nurse 5</value>
					</text>
					<text id="nurse_on_call-nurse_6-label">
						<value>nurse 6</value>
					</text>
					<text id="nurse_on_call-nurse_7-label">
						<value>nurse 7</value>
					</text>
					<text id="nurse_on_call-nurse_8-label">
						<value>nurse 8</value>
					</text>
					<text id="nurse_on_call-nurse_9-label">
						<value>nurse 9</value>
					</text>
					<text id="nurse_on_call-nurse_10-label">
						<value>nurse 10</value>
					</text>
					<text id="shift-label">
						<value>Shift</value>
					</text>
					<text id="shift-morning-label">
						<value>Morning (8am - 4pm)</value>
					</text>
					<text id="shift-afternoon-label">
						<value>Afternoon (4pm - 12am)</value>
					</text>
					<text id="shift-night-label">
						<value>Night (12am - 8am)</value>
					</text>
					<text id="on_call_doctor-label">
						<value>On-call Doctor:</value>
					</text>
					<text id="on_call_doctor-doctor_1-label">
						<value>Dr. ____ ____ (PG) (phone number)</value>
					</text>
					<text id="on_call_doctor-doctor_2-label">
						<value>Dr. ____ ____ (SR) (phone number)</value>
					</text>
					<text id="on_call_doctor-doctor_3-label">
						<value>Dr. ____ ____ (Attending) (phone number)</value>
					</text>
				</translation>
			</itext>
		<setvalue event="xforms-ready" ref="/data/meta/deviceID" value="instance('commcaresession')/session/context/deviceid"/><setvalue event="xforms-ready" ref="/data/meta/timeStart" value="now()"/><bind nodeset="/data/meta/timeStart" type="xsd:dateTime"/><setvalue event="xforms-revalidate" ref="/data/meta/timeEnd" value="now()"/><bind nodeset="/data/meta/timeEnd" type="xsd:dateTime"/><setvalue event="xforms-ready" ref="/data/meta/username" value="instance('commcaresession')/session/context/username"/><setvalue event="xforms-ready" ref="/data/meta/userID" value="instance('commcaresession')/session/context/userid"/><setvalue event="xforms-ready" ref="/data/meta/instanceID" value="uuid()"/><setvalue event="xforms-ready" ref="/data/meta/appVersion" value="instance('commcaresession')/session/context/appversion"/></model>
	</h:head>
	<h:body>
		<select1 ref="/data/nurse_on_call">
			<label ref="jr:itext('nurse_on_call-label')"/>
			<item>
				<label ref="jr:itext('nurse_on_call-nurse_1-label')"/>
				<value>nurse_1</value>
			</item>
			<item>
				<label ref="jr:itext('nurse_on_call-nurse_2-label')"/>
				<value>nurse_2</value>
			</item>
			<item>
				<label ref="jr:itext('nurse_on_call-nurse_3-label')"/>
				<value>nurse_3</value>
			</item>
			<item>
				<label ref="jr:itext('nurse_on_call-nurse_4-label')"/>
				<value>nurse_4</value>
			</item>
			<item>
				<label ref="jr:itext('nurse_on_call-nurse_5-label')"/>
				<value>nurse_5</value>
			</item>
			<item>
				<label ref="jr:itext('nurse_on_call-nurse_6-label')"/>
				<value>nurse_6</value>
			</item>
			<item>
				<label ref="jr:itext('nurse_on_call-nurse_7-label')"/>
				<value>nurse_7</value>
			</item>
			<item>
				<label ref="jr:itext('nurse_on_call-nurse_8-label')"/>
				<value>nurse_8</value>
			</item>
			<item>
				<label ref="jr:itext('nurse_on_call-nurse_9-label')"/>
				<value>nurse_9</value>
			</item>
			<item>
				<label ref="jr:itext('nurse_on_call-nurse_10-label')"/>
				<value>nurse_10</value>
			</item>
		</select1>
		<select1 ref="/data/shift">
			<label ref="jr:itext('shift-label')"/>
			<item>
				<label ref="jr:itext('shift-morning-label')"/>
				<value>morning</value>
			</item>
			<item>
				<label ref="jr:itext('shift-afternoon-label')"/>
				<value>afternoon</value>
			</item>
			<item>
				<label ref="jr:itext('shift-night-label')"/>
				<value>night</value>
			</item>
		</select1>
		<select1 ref="/data/on_call_doctor">
			<label ref="jr:itext('on_call_doctor-label')"/>
			<item>
				<label ref="jr:itext('on_call_doctor-doctor_1-label')"/>
				<value>doctor_1</value>
			</item>
			<item>
				<label ref="jr:itext('on_call_doctor-doctor_2-label')"/>
				<value>doctor_2</value>
			</item>
			<item>
				<label ref="jr:itext('on_call_doctor-doctor_3-label')"/>
				<value>doctor_3</value>
			</item>
		</select1>
	</h:body>
</h:html>